watchcode/__init__.py
watchcode/colors.py
watchcode/config.py
watchcode/io_handler.py
watchcode/matching.py
watchcode/templates.py
watchcode/trigger.py
watchcode/watchcode.py
watchcode/sounds/377017__elmasmalo1__notification-pop.wav
watchcode/sounds/456581__bumpelsnake__nameit5.wav
watchcode/templates/full.yaml
watchcode/templates/minimal.yaml
watchcode-0.1.1.dist-info/LICENSE
watchcode-0.1.1.dist-info/METADATA
watchcode-0.1.1.dist-info/WHEEL
watchcode-0.1.1.dist-info/entry_points.txt
watchcode-0.1.1.dist-info/top_level.txt
watchcode-0.1.1.dist-info/RECORD
