Metadata-Version: 2.1
Name: watchcode
Version: 0.1.1
Summary: Generic tool to solve the modify + re-run problem
Home-page: UNKNOWN
Author: Fabian Keller
Author-email: UNKNOWN
License: MIT
Platform: UNKNOWN
Requires-Dist: six
Requires-Dist: watchdog (>=0.9.0)
Requires-Dist: pyyaml (>=3.0)
Requires-Dist: pytest
Requires-Dist: pytest-cov
